intellektron_ml/__init__.py
intellektron_ml/version.py
intellektron_ml-0.0.1.dist-info/licenses/LICENSE
intellektron_ml-0.0.1.dist-info/METADATA
intellektron_ml-0.0.1.dist-info/WHEEL
intellektron_ml-0.0.1.dist-info/top_level.txt
intellektron_ml-0.0.1.dist-info/RECORD
