Metadata-Version: 2.4
Name: intellektron-ml
Version: 0.0.1
Summary: An educational package for machine learning fundamentals by Intellektron.
Author-email: Kaustav <kaustavcodes@gmail.com>
License: ﻿MIT License
Project-URL: Homepage, https://github.com/commandantekaustav/intellektron-ml
Project-URL: Bug Tracker, https://github.com/commandantekaustav/intellektron-ml/issues
Classifier: Development Status :: 2 - Pre-Alpha
Classifier: Intended Audience :: Education
Classifier: License :: OSI Approved :: MIT License
Classifier: Programming Language :: Python :: 3
Classifier: Topic :: Scientific/Engineering :: Artificial Intelligence
Requires-Python: >=3.8
License-File: LICENSE
Dynamic: license-file
